wutch/__init__.py
wutch/app.py
wutch/config.py
wutch/events.py
wutch/js/__init__.py
wutch/js/wutch.js
wutch/js/wutch_fetch.js
wutch/server.py
wutch/threaded.py
wutch/version.py
wutch/watcher.py
wutch-1.0.12.dist-info/entry_points.txt
wutch-1.0.12.dist-info/WHEEL
wutch-1.0.12.dist-info/METADATA
wutch-1.0.12.dist-info/RECORD
