Metadata-Version: 2.1
Name: wutch
Version: 1.0.12
Summary: Watch and rebuild your files like LiveServer
Home-page: https://github.com/vduseev/wutch
License: Apache-2.0
Keywords: liveserver,sphinx,rebuild,watcher,watchdog
Author: vduseev
Author-email: vagiz@duseev.com
Maintainer: vduseev
Maintainer-email: vagiz@duseev.com
Requires-Python: >=3.8,<4.0
Classifier: License :: OSI Approved :: Apache Software License
Classifier: Programming Language :: Python :: 3
Classifier: Programming Language :: Python :: 3.8
Classifier: Programming Language :: Python :: 3.9
Requires-Dist: aiofiles (>=0.6.0,<0.7.0)
Requires-Dist: aiohttp (>=3.7.3,<4.0.0)
Requires-Dist: beautifulsoup4 (>=4.9.3,<5.0.0)
Requires-Dist: ilexconf (>=0.9.5,<0.10.0)
Requires-Dist: loguru (>=0.5.3,<0.6.0)
Requires-Dist: watchdog (>=1.0.2,<2.0.0)
Project-URL: Documentation, https://wutch.readthedocs.io
Project-URL: Repository, https://github.com/vduseev/wutch
